htx/__init__.py
htx/base_model.py
htx/htx.py
htx/model_manager.py
htx/utils.py
htx/adapters/__init__.py
htx/adapters/fast_ai.py
htx/adapters/sklearn.py
tests/__init__.py
tests/conftest.py
tests/test_manager.py
tests/test_model.py
pyheartex-0.0.8.dist-info/LICENSE
pyheartex-0.0.8.dist-info/METADATA
pyheartex-0.0.8.dist-info/WHEEL
pyheartex-0.0.8.dist-info/top_level.txt
pyheartex-0.0.8.dist-info/RECORD
