Metadata-Version: 2.1
Name: pyheartex
Version: 0.0.8
Summary: Deploying machine learning for Heartex or Label Studio
Home-page: https://github.com/heartexlabs/pyheartex
Author: Heartex
Author-email: hello@heartex.ai
License: UNKNOWN
Platform: UNKNOWN
Classifier: Programming Language :: Python :: 3
Classifier: License :: OSI Approved :: MIT License
Classifier: Operating System :: OS Independent
Requires-Python: >=3.6
Requires-Dist: Flask (==1.0.2)
Requires-Dist: attrs (==19.1.0)
Requires-Dist: rq (==1.0)
Requires-Dist: numpy (>=1.16.3)
Requires-Dist: requests (==2.22.0)
